[
  {
    "title": "Adult with confirmed case of measles dies, HSE says",
    "link": "https://www.rte.ie/news/ireland/2024/0207/1431067-measles-death/",
    "isSarcastic": 0
  },
  {
    "title": "Murder probe launched into death of man in Macroom",
    "link": "https://www.rte.ie/news/ireland/2024/0207/1430864-cork-investigation/",
    "isSarcastic": 0
  },
  {
    "title": "Martin vows to tackle 'campaign of arson and criminality'",
    "link": "https://www.rte.ie/news/ireland/2024/0207/1430998-leixlip-fire/",
    "isSarcastic": 0
  },
  {
    "title": "Netanyahu rejects Hamas ceasefire proposal",
    "link": "https://www.rte.ie/news/middle-east/2024/0207/1430859-middle-east/",
    "isSarcastic": 0
  },
  {
    "title": "Hospital apology for family of woman who died from cancer",
    "link": "https://www.rte.ie/news/courts/2024/0207/1430955-hospital-apologises-over-failures-in-late-womans-care/",
    "isSarcastic": 0
  },
  {
    "title": "Watch: New rare disease awareness campaign launched",
    "link": "https://www.rte.ie/news/health/2024/0207/1431045-watch-new-rare-disease-awareness-campaign-launched/",
    "isSarcastic": 0
  },
  {
    "title": "Plan to restrict cars driving through Dublin city centre",
    "link": "https://www.rte.ie/news/dublin/2024/0207/1431029-dublin-cars/",
    "isSarcastic": 0
  },
  {
    "title": "John Bruton believed that 'every person counts' - brother",
    "link": "https://www.rte.ie/news/ireland/2024/0207/1431036-bruton-tributes/",
    "isSarcastic": 0
  },
  {
    "title": "Man jailed for attempting to meet girl he believed was 13",
    "link": "https://www.rte.ie/news/courts/2024/0207/1431021-court-child-exploitation/",
    "isSarcastic": 0
  },
  {
    "title": "Basketball Ireland outraged by anti-Semitism accusation",
    "link": "https://www.rte.ie/sport/basketball/2024/0207/1431056-basketball-ireland-outraged-by-anti-semitism-accusation/",
    "isSarcastic": 0
  },
  {
    "title": "No evidence venues currently lock exits, inquests told",
    "link": "https://www.rte.ie/news/dublin/2024/0207/1431034-stardust-inquests/",
    "isSarcastic": 0
  },
  {
    "title": "US Senate block border bill, but foreign aid may survive",
    "link": "https://www.rte.ie/news/world/2024/0207/1431058-senate-bill/",
    "isSarcastic": 0
  },
  {
    "title": "Status Yellow snow warnings extended to several counties",
    "link": "https://www.rte.ie/news/weather/2024/0207/1430877-weather-warnings/",
    "isSarcastic": 0
  },
  {
    "title": "New overcrowding record as 150 on trolleys in UHL",
    "link": "https://www.rte.ie/news/health/2024/0207/1430941-hospital-trolleys-limerick/",
    "isSarcastic": 0
  },
  {
    "title": "Man to stay away from Direct Provision centres - court",
    "link": "https://www.rte.ie/news/courts/2024/0207/1430984-kerry-court/",
    "isSarcastic": 0
  },
  {
    "title": "'Massive' Russian air attack kills five in Ukraine",
    "link": "https://www.rte.ie/news/ukraine/2024/0207/1430865-ukraine-russia/",
    "isSarcastic": 0
  },
  {
    "title": "Department will ensure enough school places - minister",
    "link": "https://www.rte.ie/news/ireland/2024/0207/1430989-school-places/",
    "isSarcastic": 0
  },
  {
    "title": "Convoys of tractors clog Barcelona as farmers block roads",
    "link": "https://www.rte.ie/news/world/2024/0207/1431010-spain-farmer-protest/",
    "isSarcastic": 0
  },
  {
    "title": "Cillian Murphy: 'Level of Irish talent extraordinary'",
    "link": "https://www.rte.ie/entertainment/2024/0207/1430913-cillian-murphy-level-of-irish-talent-extraordinary/",
    "isSarcastic": 0
  },
  {
    "title": "HSE recruitment freeze 'hampering Alzheimer's care'",
    "link": "https://www.rte.ie/news/politics/2024/0207/1431027-alzheimers-hse/",
    "isSarcastic": 0
  },
  {
    "title": "Both sides in Coombe Hospital dispute invited to WRC",
    "link": "https://www.rte.ie/news/health/2024/0207/1431041-coombe-hospital-wrc/",
    "isSarcastic": 0
  },
  {
    "title": "Bail application from man accused of attacking wife",
    "link": "https://www.rte.ie/news/courts/2024/0207/1431001-cork-court/",
    "isSarcastic": 0
  },
  {
    "title": "State funeral to be held for John Bruton in Co Meath",
    "link": "https://www.rte.ie/news/ireland/2024/0207/1430993-bruton-funeral/",
    "isSarcastic": 0
  },
  {
    "title": "World has entered age of chaos, UN chief says",
    "link": "https://www.rte.ie/news/world/2024/0207/1431009-guterres-un/",
    "isSarcastic": 0
  },
  {
    "title": "Scorpion stowaway found in Wicklow woman's bag",
    "link": "https://www.rte.ie/news/leinster/2024/0207/1430888-wicklow-scorpion/",
    "isSarcastic": 0
  },
  {
    "title": "Mapped: The fires linked to accommodation for migrants",
    "link": "https://www.rte.ie/news/primetime/2024/0207/1431003-mapped-the-fires-linked-to-accommodation-for-migrants/",
    "isSarcastic": 0
  },
  {
    "title": "IMO gives 'guarded welcome' to new NCHD report",
    "link": "https://www.rte.ie/news/2024/0207/1431024-imo-nchd/",
    "isSarcastic": 0
  },
  {
    "title": "Ireland failed to comply with online terrorism rules - EU",
    "link": "https://www.rte.ie/news/ireland/2024/0207/1430991-ireland-online-terrorism/",
    "isSarcastic": 0
  },
  {
    "title": "\u20ac290 million to go towards active travel projects in 2024",
    "link": "https://www.rte.ie/news/ireland/2024/0207/1430966-active-travel/",
    "isSarcastic": 0
  },
  {
    "title": "New search and rescue operator granted air certificate",
    "link": "https://www.rte.ie/news/ireland/2024/0207/1431013-bristow-coast-guard/",
    "isSarcastic": 0
  },
  {
    "title": "Temple Street review widened to include extra cases",
    "link": "https://www.rte.ie/news/health/2024/0207/1430945-temple-street-childrens-hospital/",
    "isSarcastic": 0
  },
  {
    "title": "FF accused of 'male, pale and stale' MEP theme",
    "link": "https://www.rte.ie/news/politics/2024/0207/1430990-eu-elections/",
    "isSarcastic": 0
  },
  {
    "title": "Eight-year-old Charlie has world at his 'Fastest Feet'",
    "link": "https://www.rte.ie/news/ireland/2024/0207/1430867-ireland-fastest/",
    "isSarcastic": 0
  },
  {
    "title": "EU's first directive on violence against women agreed",
    "link": "https://www.rte.ie/news/ireland/2024/0207/1430949-eu-directive/",
    "isSarcastic": 0
  },
  {
    "title": "Dublin Airport expansion 'essential' for economic growth",
    "link": "https://www.rte.ie/news/ireland/2024/0207/1430933-dublin-airport/",
    "isSarcastic": 0
  },
  {
    "title": "Haley loses Nevada primary to 'none of these candidates'",
    "link": "https://www.rte.ie/news/us/2024/0207/1430868-us-elections/",
    "isSarcastic": 0
  },
  {
    "title": "Blasts kill 26 in Pakistan on eve of general election",
    "link": "https://www.rte.ie/news/world/2024/0207/1430915-pakistan-blast/",
    "isSarcastic": 0
  },
  {
    "title": "Ryanair again wins court challenge against KLM bailout",
    "link": "https://www.rte.ie/news/business/2024/0207/1430911-ryanair-again-wins-court-challenge-against-klm-bailout/",
    "isSarcastic": 0
  },
  {
    "title": "Climate expert: Targets a 'stepping stone' to net zero",
    "link": "https://www.rte.ie/news/ireland/2024/0207/1430910-climate-report/",
    "isSarcastic": 0
  },
  {
    "title": "UK parole board refuses Gary Glitter's bid to be freed",
    "link": "https://www.rte.ie/news/uk/2024/0207/1430923-gary-glitter/",
    "isSarcastic": 0
  },
  {
    "title": "Flogas Energy latest supplier to cut residential prices",
    "link": "https://www.rte.ie/news/business/2024/0207/1430792-flogas-energy-latest-supplier-to-cut-residential-prices/",
    "isSarcastic": 0
  },
  {
    "title": "State breaches rights over homelessness, poverty - IHREC",
    "link": "https://www.rte.ie/news/ireland/2024/0207/1430884-human-rights/",
    "isSarcastic": 0
  },
  {
    "title": "\u20ac84m announced for research at Technological Universities",
    "link": "https://www.rte.ie/news/business/2024/0207/1430828-technical-universities/",
    "isSarcastic": 0
  },
  {
    "title": "Tech firms faced with wage pressures and talent shortages",
    "link": "https://www.rte.ie/news/business/2024/0207/1430829-tech-staffing/",
    "isSarcastic": 0
  },
  {
    "title": "Man, 61, charged in connection with Dublin riots",
    "link": "https://www.rte.ie/news/courts/2024/0206/1430778-dublin-riots-court/",
    "isSarcastic": 0
  },
  {
    "title": "EU Commission recommends 90% emissions cut by 2040",
    "link": "https://www.rte.ie/news/europe/2024/0206/1430648-eu-climate/",
    "isSarcastic": 0
  },
  {
    "title": "Bolts missing from Boeing plane door, report finds",
    "link": "https://www.rte.ie/news/us/2024/0206/1430840-plane-door/",
    "isSarcastic": 0
  },
  {
    "title": "Trump condemns 'nation-destroying' prosecution ruling",
    "link": "https://www.rte.ie/news/us/2024/0206/1430786-donald-trump/",
    "isSarcastic": 0
  },
  {
    "title": "MMR catch-up programme for students being explored",
    "link": "https://www.rte.ie/news/health/2024/0206/1430641-politics/",
    "isSarcastic": 0
  }
]